[
	{
		"__TYPE__": "SharedSliceContent",
		"variation": "default",
		"primary": {
			"title": {
				"__TYPE__": "FieldContent",
				"value": "shall",
				"type": "Text"
			},
			"image": {
				"origin": {
					"id": "main",
					"url": "https://images.unsplash.com/photo-1547082299-de196ea013d6",
					"width": 4272,
					"height": 2848
				},
				"url": "https://images.unsplash.com/photo-1547082299-de196ea013d6",
				"width": 4272,
				"height": 2848,
				"edit": {
					"zoom": 1,
					"crop": {
						"x": 0,
						"y": 0
					},
					"background": "transparent"
				},
				"credits": null,
				"alt": null,
				"__TYPE__": "ImageContent",
				"thumbnails": {}
			},
			"cta_title": {
				"__TYPE__": "FieldContent",
				"value": "love",
				"type": "Text"
			},
			"cta_text": {
				"__TYPE__": "FieldContent",
				"value": "milk",
				"type": "Text"
			}
		},
		"items": []
	}
]